nbautoexport/__init__.py
nbautoexport/__main__.py
nbautoexport/clean.py
nbautoexport/export.py
nbautoexport/jupyter_config.py
nbautoexport/nbautoexport.py
nbautoexport/sentinel.py
nbautoexport/utils.py
nbautoexport-0.5.2.dist-info/entry_points.txt
nbautoexport-0.5.2.dist-info/WHEEL
nbautoexport-0.5.2.dist-info/METADATA
nbautoexport-0.5.2.dist-info/licenses/LICENSE
nbautoexport-0.5.2.dist-info/RECORD
