Metadata-Version: 2.1
Name: nbautoexport
Version: 0.5.2
Summary: Automatically export Jupyter notebooks to various file formats (.py, .html, and more) on save.
License: MIT
Keywords: nbautoexport,jupyter,nbconvert
Author-email: DrivenData <info@drivendata.org>
Requires-Python: >=3.7
Classifier: Framework :: Jupyter
Classifier: Intended Audience :: Developers
Classifier: Intended Audience :: Science/Research
Classifier: License :: OSI Approved :: MIT License
Classifier: Operating System :: OS Independent
Classifier: Programming Language :: Python :: 3
Classifier: Programming Language :: Python :: 3.10
Classifier: Programming Language :: Python :: 3.11
Classifier: Programming Language :: Python :: 3.7
Classifier: Programming Language :: Python :: 3.8
Classifier: Programming Language :: Python :: 3.9
Requires-Dist: importlib_metadata; python_version < "3.8"
Requires-Dist: jupyter_core
Requires-Dist: nbconvert>=5.6.1
Requires-Dist: nbformat
Requires-Dist: notebook
Requires-Dist: packaging
Requires-Dist: pydantic
Requires-Dist: traitlets
Requires-Dist: typer>=0.3.0
Project-URL: Bug Tracker, https://github.com/drivendataorg/nbautoexport/issues
Project-URL: Changelog, https://nbautoexport.drivendata.org/stable/changelog/
Project-URL: Documentation, https://nbautoexport.drivendata.org/
Project-URL: Homepage, https://github.com/drivendataorg/nbautoexport
Project-URL: Repository, https://github.com/drivendataorg/nbautoexport
